autora/synthetic/utilities.py
autora/synthetic/abstract/template_experiment.py
autora/synthetic/economics/expected_value_theory.py
autora/synthetic/economics/prospect_theory.py
autora/synthetic/psychophysics/weber_fechner_law.py
autora_synthetic_data-1.0.0a6.dist-info/METADATA
autora_synthetic_data-1.0.0a6.dist-info/WHEEL
autora_synthetic_data-1.0.0a6.dist-info/top_level.txt
autora_synthetic_data-1.0.0a6.dist-info/RECORD
