Metadata-Version: 2.1
Name: autora-synthetic-data
Version: 1.0.0a6
Summary: AutoRA Synthetic Data
License: MIT License
Project-URL: homepage, http://www.empiricalresearch.ai
Project-URL: repository, https://github.com/AutoResearch/autora-synthetic-data
Project-URL: documentation, https://autoresearch.github.io/autora-synthetic-data/
Requires-Dist: autora-core
Provides-Extra: dev
Requires-Dist: autora-synthetic-data[test] ; extra == 'dev'
Requires-Dist: autora-core[dev] ; extra == 'dev'
Requires-Dist: autora-workflow ; extra == 'dev'
Requires-Dist: scikit-learn ; extra == 'dev'
Provides-Extra: test
Requires-Dist: pytest ; extra == 'test'
Requires-Dist: hypothesis ; extra == 'test'
